lineup/__init__.py
lineup/detail.py
lineup-0.0.2.dist-info/licenses/LICENSE
lineup-0.0.2.dist-info/METADATA
lineup-0.0.2.dist-info/WHEEL
lineup-0.0.2.dist-info/top_level.txt
lineup-0.0.2.dist-info/RECORD
