Metadata-Version: 2.4
Name: lineup
Version: 0.0.2
Summary: A tool to customize exception tracebacks to show file, line number, and code line
Home-page: https://github.com/TaireruLLC/lineup
Author: Taireru LLC
Author-email: tairerullc@gmail.com
License: MIT
Classifier: Programming Language :: Python :: 3
Classifier: Operating System :: OS Independent
Requires-Python: >=3.6
License-File: LICENSE
Dynamic: author
Dynamic: author-email
Dynamic: classifier
Dynamic: description
Dynamic: description-content-type
Dynamic: home-page
Dynamic: license
Dynamic: license-file
Dynamic: requires-python
Dynamic: summary
